Workbook

Sheet Assumptions
A1: Cursor Enterprise – Budget Assumptions
A3: Seat Structure
A4: Input | B4: Value | C4: Unit | D4: Note
A5: Total users | B5: 40 | C5: Users | D5: Phase 1 – Q2 2026
A6: CLS-NET users | B6: 20 | C6: Users | D6: 50% of total
A7: CLS-DIRECT users | B7: 20 | C7: Users | D7: 50% of total
A8: Premium seats (total) | B8: 10 | C8: Users | D8: 5 per group (heavy agent users)
A9: Standard seats (total) | B9: 30 | C9: Users | D9: 15 per group (lighter usage)
A10: Standard seat price | B10: 40 | C10: $/user/month | D10: Source: Cursor pricing sheet
A11: Premium seat price | B11: 120 | C11: $/user/month | D11: 5× Standard included usage
A13: API Spend Tiers (model token budget, on top of seat cost)
A14: Input | B14: Value | C14: Unit | D14: Note
A15: $75 tier – Standard API budget/user | B15: 75 | C15: $/user/month | D15: Lighter usage profile
A16: $75 tier – Premium API budget/user | B16: 75 | C16: $/user/month | D16: Same rate; more headroom via seat
A17: $125 tier – Standard API budget/user | B17: 125 | C17: $/user/month | D17: Upgrade scenario
A18: $125 tier – Premium API budget/user | B18: 125 | C18: $/user/month | D18: Recommended for power users
A19: Cursor Token Rate (third-party) | B19: 0.25 | C19: $/M tokens | D19: Surcharge on non-Cursor models (Claude, GPT, Gemini)

Sheet Phase 1 – 40 Users
A1: Phase 1 – 40 Users (Q2 2026) | Budget Controls
A3: A. Seat Costs
A4: Item | B4: CLS-NET | C4: CLS-DIRECT | D4: Total | E4: Annual
A5: Standard seats (count) | B5: =Assumptions!B9/2 -> 15 | C5: =Assumptions!B9/2 -> 15 | D5: =B5+C5 -> 30
A6: Premium seats (count) | B6: =Assumptions!B8/2 -> 5 | C6: =Assumptions!B8/2 -> 5 | D6: =B6+C6 -> 10
A7: Standard seat cost / month | B7: =B5*Assumptions!B10 -> 600 | C7: =C5*Assumptions!B10 -> 600 | D7: =B7+C7 -> 1200 | E7: =D7*12 -> 14400
A8: Premium seat cost / month | B8: =B6*Assumptions!B11 -> 600 | C8: =C6*Assumptions!B11 -> 600 | D8: =B8+C8 -> 1200 | E8: =D8*12 -> 14400
A9: Total seat cost / month | B9: =B7+B8 -> 1200 | C9: =C7+C8 -> 1200 | D9: =B9+C9 -> 2400 | E9: =D9*12 -> 28800
A11: B. API Spend Budget (model token consumption, on top of seat cost)
A12: Item | B12: $75 Tier / month | C12: $125 Tier / month | D12: $75 Tier / year | E12: $125 Tier / year
A13: Standard users API budget (30 users) | B13: =Assumptions!B9*Assumptions!B15 -> 2250 | C13: =Assumptions!B9*Assumptions!B17 -> 3750 | D13: =B13*12 -> 27000 | E13: =C13*12 -> 45000
A14: Premium users API budget (10 users) | B14: =Assumptions!B8*Assumptions!B16 -> 750 | C14: =Assumptions!B8*Assumptions!B18 -> 1250 | D14: =B14*12 -> 9000 | E14: =C14*12 -> 15000
A15: Total monthly API pool | B15: =B13+B14 -> 3000 | C15: =C13+C14 -> 5000 | D15: =B15*12 -> 36000 | E15: =C15*12 -> 60000
A16: Per-group pool — CLS-NET & CLS-DIRECT each | B16: =B15/2 -> 1500 | C16: =C15/2 -> 2500 | D16: =B16*12 -> 18000 | E16: =C16*12 -> 30000
A19: C. Total Cost of Ownership — Phase 1 (1 Year, per pricing sheet)
A20: Component | B20: $75 Tier | C20: $125 Tier | D20: Note
A21: Annual seat cost (40 × $40 × 12) | B21: =D9*12 -> 28800 | C21: =D9*12 -> 28800 | D21: Same for both tiers
A22: Annual API commitment | B22: =D15*12 -> 432000 | C22: =E15*12 -> 720000 | D22: 30 Std + 10 Prem × tier rate
A23: Seat discount — Phase 1 | B23: 0 | C23: 0 | D23: 0% at 40 users (per pricing sheet)
A24: API discount — Phase 1 | B24: 0 | C24: 0 | D24: 0% at 40 users (per pricing sheet)
A25: TOTAL Annual Cost | B25: =B21+B22-B23-B24 -> 460800 | C25: =C21+C22-C23-C24 -> 748800 | D25: ✓ Matches pricing sheet: $55,200 / $79,200
A28: D. Spend Limits (Monthly, per User / Group)
A29: User / Group type | B29: $75 Tier ($) | C29: $125 Tier ($) | D29: Rule | E29: Action if breached
A30: Team default (unassigned users) | B30: 40 | C30: 60 | D30: Safety net — always the lowest limit | E30: Usage stops; admin notified
A31: Standard seat member | B31: 75 | C31: 125 | D31: 1× tier API budget | E31: Usage stops until cycle reset
A32: Premium seat member | B32: 150 | C32: 250 | D32: 2× Standard limit | E32: Usage stops until cycle reset
A33: Per-group pool — CLS-NET | B33: 1500 | C33: 2500 | D33: Sum of group members' limits | E33: Admin review; raise or restrict
A34: Per-group pool — CLS-DIRECT | B34: 1500 | C34: 2500 | D34: Sum of group members' limits | E34: Admin review; raise or restrict
A35: Team-wide monthly pool | B35: 3000 | C35: 5000 | D35: Total API commitment ÷ 12 | E35: Escalate to Finance

Sheet Scale Plan – 40 to 400
A1: Cursor Enterprise – Scale Plan: 40 → 400 Users
A3: Phase Summary
A4: Phase | B4: Quarter | C4: Seats | D4: Std seats | E4: Prem seats | F4: Monthly seat cost ($) | G4: Annual seat cost ($) | H4: API annual $75 tier ($) | I4: API annual $125 tier ($) | J4: Seat disc %
A5: Phase 1 | B5: Q2 2026 | C5: 40 | D5: 30 | E5: 10 | F5: =D5*Assumptions!$B$10+E5*Assumptions!$B$11 -> 2400 | G5: =F5*12*(1-$B$22) -> 28800 | H5: =(D5*Assumptions!$B$15+E5*Assumptions!$B$16)*12*(1-$D$22) -> 36000 | I5: =(D5*Assumptions!$B$17+E5*Assumptions!$B$18)*12*(1-$E$22) -> 60000 | J5: =$B$22 -> 0
A6: Phase 2 | B6: Q3 2026 | C6: 100 | D6: 75 | E6: 25 | F6: =D6*Assumptions!$B$10+E6*Assumptions!$B$11 -> 6000 | G6: =F6*12*(1-$B$23) -> 61200 | H6: =(D6*Assumptions!$B$15+E6*Assumptions!$B$16)*12*(1-$D$23) -> 89100 | I6: =(D6*Assumptions!$B$17+E6*Assumptions!$B$18)*12*(1-$E$23) -> 147750 | J6: =$B$23 -> 0.15
A7: Phase 3 | B7: Q4 2026 | C7: 200 | D7: 150 | E7: 50 | F7: =D7*Assumptions!$B$10+E7*Assumptions!$B$11 -> 12000 | G7: =F7*12*(1-$B$24) -> 100800 | H7: =(D7*Assumptions!$B$15+E7*Assumptions!$B$16)*12*(1-$D$24) -> 177300 | I7: =(D7*Assumptions!$B$17+E7*Assumptions!$B$18)*12*(1-$E$24) -> 291000 | J7: =$B$24 -> 0.3
A8: Phase 4 | B8: Q1 2027 | C8: 400 | D8: 300 | E8: 100 | F8: =D8*Assumptions!$B$10+E8*Assumptions!$B$11 -> 24000 | G8: =F8*12*(1-$B$25) -> 57600 | H8: =(D8*Assumptions!$B$15+E8*Assumptions!$B$16)*12*(1-$D$25) -> 349200 | I8: =(D8*Assumptions!$B$17+E8*Assumptions!$B$18)*12*(1-$E$25) -> 570000 | J8: =$B$25 -> 0.8
A10: Total Cost of Ownership (Seat + API, after discounts)
A11: Phase | B11: Quarter | C11: Seats | D11: Seat cost (post-disc) | E11: API cost $75 | F11: API cost $125 | G11: TOTAL $75 tier | H11: TOTAL $125 tier | I11: Δ $125 vs $75 | J11: Recommended tier
A12: =A5 -> Phase 1 | B12: =B5 -> Q2 2026 | C12: =C5 -> 40 | D12: =G5 -> 28800 | E12: =H5 -> 36000 | F12: =I5 -> 60000 | G12: =G5+H5 -> 64800 | H12: =G5+I5 -> 88800 | I12: =H12-G12 -> 24000 | J12: $75 – start here; review after 60 days
A13: =A6 -> Phase 2 | B13: =B6 -> Q3 2026 | C13: =C6 -> 100 | D13: =G6 -> 61200 | E13: =H6 -> 89100 | F13: =I6 -> 147750 | G13: =G6+H6 -> 150300 | H13: =G6+I6 -> 208950 | I13: =H13-G13 -> 58650 | J13: Review: upgrade power users to $125
A14: =A7 -> Phase 3 | B14: =B7 -> Q4 2026 | C14: =C7 -> 200 | D14: =G7 -> 100800 | E14: =H7 -> 177300 | F14: =I7 -> 291000 | G14: =G7+H7 -> 278100 | H14: =G7+I7 -> 391800 | I14: =H14-G14 -> 113700 | J14: $125 recommended for Premium users
A15: =A8 -> Phase 4 | B15: =B8 -> Q1 2027 | C15: =C8 -> 400 | D15: =G8 -> 57600 | E15: =H8 -> 349200 | F15: =I8 -> 570000 | G15: =G8+H8 -> 406800 | H15: =G8+I8 -> 627600 | I15: =H15-G15 -> 220800 | J15: $125 – seat discount covers seat cost
A20: Discount Assumptions (from pricing sheet — edit cells in blue)
A21: Phase | B21: Seat disc $75 | C21: Seat disc $125 | D21: API disc $75 | E21: API disc $125 | F21: Source
A22: Phase 1 | B22: 0 | C22: 0 | D22: 0 | E22: 0 | F22: Source: pricing sheet email
A23: Phase 2 | B23: 0.15 | C23: 0.25 | D23: 0.01 | E23: 0.015 | F23: Source: pricing sheet email
A24: Phase 3 | B24: 0.3 | C24: 0.5 | D24: 0.015 | E24: 0.03 | F24: Source: pricing sheet email
A25: Phase 4 | B25: 0.8 | C25: 1 | D25: 0.03 | E25: 0.05 | F25: Source: pricing sheet email

Sheet Spend Alerts & Controls
A1: Cursor Enterprise – Spend Alerts & Governance Controls
A3: Spend Alert Thresholds (email notifications — do not stop usage)
A4: Alert | B4: Threshold | C4: $75 trigger ($) | D4: $125 trigger ($) | E4: Recipients | F4: Action
A5: Team monthly – early warning | B5: 50% | C5: ='Phase 1 – 40 Users'!B15*0.5 -> 1500 | D5: ='Phase 1 – 40 Users'!C15*0.5 -> 2500 | E5: Admins + Finance | F5: Monitor
A6: Team monthly – caution | B6: 80% | C6: ='Phase 1 – 40 Users'!B15*0.8 -> 2400 | D6: ='Phase 1 – 40 Users'!C15*0.8 -> 4000 | E6: Admins + Finance | F6: Review top 5 spenders
A7: Team monthly – critical | B7: 100% | C7: ='Phase 1 – 40 Users'!B15*1 -> 3000 | D7: ='Phase 1 – 40 Users'!C15*1 -> 5000 | E7: Admins + Finance + Management | F7: Escalate; consider raising limit
A8: Member spend – caution | B8: 80% of limit | C8: ='Phase 1 – 40 Users'!B30*0.8 -> 32 | D8: ='Phase 1 – 40 Users'!C30*0.8 -> 48 | E8: Member + Group admin | F8: Member reviews own usage
A9: Annual pace >110% straight-line | B9: 110% pace | C9: =36000/12*1.1 -> 3300 | D9: =60000/12*1.1 -> 5500 | E9: Finance (via Admin API) | F9: Finance review; risk of overrun
A12: Governance Checklist (tick Status as you go)
A13: Control | B13: Required setting | C13: Owner | D13: Status | E13: Priority | F13: Notes
A14: SSO enforced | B14: Enabled | C14: Admin | D14: To do | E14: P1 – Day 1 | F14: Disable invite links; verified domains only
A15: Only Admins Edit Usage Settings | B15: Enabled | C15: Admin | D15: To do | E15: P1 – Day 1 | F15: Prevents users raising own spend limits
A16: Invite links disabled | B16: Disabled | C16: Admin | D16: To do | E16: P1 – Day 1 | F16: Use SSO or domain matching instead
A17: CLS-NET group created | B17: Done | C17: Admin | D17: To do | E17: P1 – Day 1 | F17: Assign 20 users; set group spend limit
A18: CLS-DIRECT group created | B18: Done | C18: Admin | D18: To do | E18: P1 – Day 1 | F18: Assign 20 users; set group spend limit
A19: Finance Unpaid Admin seats | B19: Assigned | C19: Admin | D19: To do | E19: P1 – Week 1 | F19: Free seats; full billing visibility
A20: Admin API key created | B20: Created | C20: Admin/FinOps | D20: To do | E20: P1 – Week 1 | F20: Required for per-group reporting pipeline
A21: Default model → Composer/Grok | B21: Configured | C21: Admin | D21: To do | E21: P1 – Week 1 | F21: Avoids $0.25/M Cursor Token Rate surcharge
A22: Spend alerts configured | B22: Enabled | C22: Admin | D22: To do | E22: P1 – Week 1 | F22: 50% / 80% / 100% thresholds
A23: Per-group chargeback report | B23: Built | C23: FinOps | D23: To do | E23: P1 – Week 2 | F23: Admin API → GCP/AWS FinOps pipeline
A24: Audit log monitoring | B24: Active | C24: Admin | D24: To do | E24: P1 – Week 2 | F24: Watch admin_only_usage_pricing events
... A26: Dynamic Spend Limits enabled | B26: Enabled | C26: Admin | D26: Future | E26: Phase 3 | F26: Auto-scales limits with headcount
