Workbook

Sheet Management Summary
A1: GitHub Enterprise POC: Final Cost and No-Surprise Billing Plan
A3: Confirmed POC design
A4: Enterprise users | B4: 40 | C4: GitHub Enterprise licence | D4: $20/user/month | E4: Current base monthly cost | F4: =B4*20 -> 800 | G4: Annual base cost | H4: =F4*12 -> 9600 | I4: PO rate
A5: NET organisation | B5: 20-user planning split | C5: Repositories | D5: 40 | E5: Identity | F5: Okta / Azure AD | G5: Current enabled scope | H5: Repositories only | I5: Editable user split
A6: DIRECT organisation | B6: 20-user planning split | C6: Repositories | D6: 80 | E6: Identity | F6: Okta / Azure AD | G6: Current enabled scope | H6: Repositories only | I6: Editable user split
A9: 12-month planning result
A10: Measure | B10: Value | C10: Measure | D10: Value | E10: Measure | F10: Value | G10: Measure | H10: Value | I10: Comment
A11: Months 1-6 scope | B11: Repositories only | C11: Months 7-12 scope | D11: Repositories + Actions | E11: Base monthly cost | F11: =Assumptions!B4*Assumptions!B5 -> 800 | G11: Actions monthly planning cost | H11: =MAX(Assumptions!B4*Assumptions!B8-Assumptions!B10,0)*Assumptions!B9+Assumptions!B11 -> 120 | I11: Actions uses conservative zero included-minutes assumption
A12: 12-month base licence cost | B12: =Assumptions!B4*Assumptions!B5*12 -> 9600 | C12: Six-month Actions cost | D12: =H11*6 -> 720 | E12: Total prorated 12-month cost | F12: =B12+D12 -> 10320 | G12: Current disabled-service cost | H12: $0 | I12: Copilot, Codespaces, Pages and other products kept off
A15: Management recommendation
A16: 1. Keep the POC at 40 approved seats. The current predictable cost is 40 x $20 = $800 per month, or $9,600 for 12 months.
A17: 2. Repositories are the only enabled capability. Set $0 budgets or technical disablement for Actions, Codespaces, Copilot AI overage and any other exposed metered SKU.
A18: 3. Before Actions is enabled in month 7, replace the conservative usage assumption with pilot telemetry and confirm included minutes from the PO. Create separate NET and DIRECT Actions budgets.
A19: 4. Review billing daily during active tests, weekly otherwise, and perform a finance pre-close before the invoice is issued.
A22: Colour key
A23: Yellow / blue text | B23: Editable user or commercial input
A24: Green | B24: Formula / calculated value
A25: Purple | B25: Budget or control decision
A26: Gray | B26: Static or confirmed configuration

Sheet Setup & Allocation
A1: POC Setup, Organisations and Identity Integration
A3: Level | B3: Name | C3: Users allocated | D3: Repositories | E3: Teams | F3: Identity source | G3: Provisioning | H3: Admin model | I3: Cost treatment
A4: Enterprise | B4: GitHub Enterprise POC | C4: 40 | D4: 120 | E4: Multiple | F4: Okta / Azure Active Directory | G4: SSO plus SCIM/group mapping | H4: 1 Enterprise Administrator | I4: 40 enterprise seats at $20/user/month
A5: Organisation | B5: NET | C5: 20 | D5: 40 | E5: Organisation-specific teams | F5: Okta / Azure Active Directory | G5: IdP groups mapped to GitHub teams | H5: Organisation owner(s) delegated | I5: 50% of shared seat cost for planning
A6: Organisation | B6: DIRECT | C6: 20 | D6: 80 | E6: Organisation-specific teams | F6: Okta / Azure Active Directory | G6: IdP groups mapped to GitHub teams | H6: Organisation owner(s) delegated | I6: 50% of shared seat cost for planning
A9: Architecture note
A10: Repository count is shown for planning and governance, but it does not change the $20 per-user base licence calculation. Users authenticate through Okta/Azure Active Directory, with groups mapped to organisations and teams. The 20/20 user allocation is an editable planning split because only the total population of 40 was confirmed.

Sheet Assumptions
A1: Commercial and Usage Assumptions
A3: Input | B3: Value | C3: Unit | D3: Enabled now? | E3: Enable month | F3: Source / status | G3: Notes
A4: POC users | B4: 40 | C4: Users | D4: Yes | E4: 1 | F4: POC design | G4: Editable
A5: Enterprise licence per user / month | B5: 20 | C5: USD | D5: Yes | E5: 1 | F5: PO provided by user | G5: Contracted PO rate
A6: Forecast months | B6: 12 | C6: Months | D6: Yes | E6: 1 | F6: Planning assumption | G6: 12-month view
A7: Actions enable month | B7: 7 | C7: Month number | D7: Future | E7: 7 | F7: User plan | G7: Enabled after six months
A8: Actions minutes per user / month | B8: 500 | C8: Minutes | D8: Future | E8: 7 | F8: Planning assumption | G8: Conservative placeholder; replace with pilot telemetry
A9: Actions Linux 2-core rate per minute | B9: 0.006 | C9: USD | D9: Future | E9: 7 | F9: GitHub official runner pricing | G9: Before any included allowance
A10: Included Actions minutes per month | B10: 0 | C10: Minutes | D10: TBD | E10: 7 | F10: PO / billing entitlement | G10: Set to zero conservatively until PO entitlement is confirmed
A11: Actions artifact/storage monthly allowance | B11: 0 | C11: USD | D11: TBD | E11: 7 | F11: PO / billing entitlement | G11: Enter expected overage only if known
A12: Copilot Business reference price per user / month | B12: 19 | C12: USD | D12: No | F12: GitHub pricing calculator | G12: Illustrative only; use PO rate if enabled
A13: Copilot enabled users | B13: 0 | C13: Users | D13: No | F13: POC scope | G13: Disabled
A14: Codespaces 2-core hourly rate | B14: 0.18 | C14: USD | D14: No | F14: GitHub pricing calculator | G14: Illustrative only
A15: Codespaces hours per enabled user / month | B15: 20 | C15: Hours | D15: No | F15: Planning assumption | G15: Illustrative only
A16: Codespaces enabled users | B16: 0 | C16: Users | D16: No | F16: POC scope | G16: Disabled
A17: Codespaces storage per enabled user | B17: 10 | C17: GiB-month | D17: No | F17: Planning assumption | G17: Illustrative only
A18: Codespaces storage rate | B18: 0.07 | C18: USD/GiB-month | D18: No | F18: GitHub pricing calculator | G18: Illustrative only
A19: GitHub Pages incremental cost | B19: 0 | C19: USD/month | D19: No | F19: Planning treatment | G19: No separate metered cost modelled; validate bandwidth/build terms in PO before enablement
A20: Other metered services allowance | B20: 0 | C20: USD/month | D20: No | F20: POC scope | G20: Packages, LFS, GHAS and other services not enabled

Sheet 12-Month Prorated Plan
A1: 12-Month Prorated Cost Plan: Repositories Now, Actions from Month 7
A3: Month | B3: Phase | C3: Users | D3: NET users | E3: DIRECT users | F3: Base licences | G3: Actions minutes | H3: Included minutes | I3: Billable minutes | J3: Actions compute | K3: Actions storage | L3: Copilot | M3: Codespaces | N3: Pages / other | O3: Total
A4: Month 1 | B4: Repositories only | C4: =Assumptions!$B$4 -> 40 | D4: =ROUND(C4/2,0) -> 20 | E4: =C4-D4 -> 20 | F4: =C4*Assumptions!$B$5 -> 800 | G4: =IF(1<Assumptions!$B$7,0,C4*Assumptions!$B$8) -> 0 | H4: =IF(G4=0,0,Assumptions!$B$10) -> 0 | I4: =MAX(G4-H4,0) -> 0 | J4: =I4*Assumptions!$B$9 -> 0 | K4: =IF(G4=0,0,Assumptions!$B$11) -> 0 | L4: =Assumptions!$B$15*Assumptions!$B$14 -> 3.6 | M4: =Assumptions!$B$18*(Assumptions!$B$16*Assumptions!$B$17+Assumptions!$B$19*Assumptions!$B$20) -> 0 | N4: =Assumptions!$B$21+Assumptions!$B$22 -> 0 | O4: =SUM(F4,N4)+SUM(J4:M4) -> 803.6
A5: Month 2 | B5: Repositories only | C5: =Assumptions!$B$4 -> 40 | D5: =ROUND(C5/2,0) -> 20 | E5: =C5-D5 -> 20 | F5: =C5*Assumptions!$B$5 -> 800 | G5: =IF(2<Assumptions!$B$7,0,C5*Assumptions!$B$8) -> 0 | H5: =IF(G5=0,0,Assumptions!$B$10) -> 0 | I5: =MAX(G5-H5,0) -> 0 | J5: =I5*Assumptions!$B$9 -> 0 | K5: =IF(G5=0,0,Assumptions!$B$11) -> 0 | L5: =Assumptions!$B$15*Assumptions!$B$14 -> 3.6 | M5: =Assumptions!$B$18*(Assumptions!$B$16*Assumptions!$B$17+Assumptions!$B$19*Assumptions!$B$20) -> 0 | N5: =Assumptions!$B$21+Assumptions!$B$22 -> 0 | O5: =SUM(F5,N5)+SUM(J5:M5) -> 803.6
A6: Month 3 | B6: Repositories only | C6: =Assumptions!$B$4 -> 40 | D6: =ROUND(C6/2,0) -> 20 | E6: =C6-D6 -> 20 | F6: =C6*Assumptions!$B$5 -> 800 | G6: =IF(3<Assumptions!$B$7,0,C6*Assumptions!$B$8) -> 0 | H6: =IF(G6=0,0,Assumptions!$B$10) -> 0 | I6: =MAX(G6-H6,0) -> 0 | J6: =I6*Assumptions!$B$9 -> 0 | K6: =IF(G6=0,0,Assumptions!$B$11) -> 0 | L6: =Assumptions!$B$15*Assumptions!$B$14 -> 3.6 | M6: =Assumptions!$B$18*(Assumptions!$B$16*Assumptions!$B$17+Assumptions!$B$19*Assumptions!$B$20) -> 0 | N6: =Assumptions!$B$21+Assumptions!$B$22 -> 0 | O6: =SUM(F6,N6)+SUM(J6:M6) -> 803.6
A7: Month 4 | B7: Repositories only | C7: =Assumptions!$B$4 -> 40 | D7: =ROUND(C7/2,0) -> 20 | E7: =C7-D7 -> 20 | F7: =C7*Assumptions!$B$5 -> 800 | G7: =IF(4<Assumptions!$B$7,0,C7*Assumptions!$B$8) -> 0 | H7: =IF(G7=0,0,Assumptions!$B$10) -> 0 | I7: =MAX(G7-H7,0) -> 0 | J7: =I7*Assumptions!$B$9 -> 0 | K7: =IF(G7=0,0,Assumptions!$B$11) -> 0 | L7: =Assumptions!$B$15*Assumptions!$B$14 -> 3.6 | M7: =Assumptions!$B$18*(Assumptions!$B$16*Assumptions!$B$17+Assumptions!$B$19*Assumptions!$B$20) -> 0 | N7: =Assumptions!$B$21+Assumptions!$B$22 -> 0 | O7: =SUM(F7,N7)+SUM(J7:M7) -> 803.6
A8: Month 5 | B8: Repositories only | C8: =Assumptions!$B$4 -> 40 | D8: =ROUND(C8/2,0) -> 20 | E8: =C8-D8 -> 20 | F8: =C8*Assumptions!$B$5 -> 800 | G8: =IF(5<Assumptions!$B$7,0,C8*Assumptions!$B$8) -> 0 | H8: =IF(G8=0,0,Assumptions!$B$10) -> 0 | I8: =MAX(G8-H8,0) -> 0 | J8: =I8*Assumptions!$B$9 -> 0 | K8: =IF(G8=0,0,Assumptions!$B$11) -> 0 | L8: =Assumptions!$B$15*Assumptions!$B$14 -> 3.6 | M8: =Assumptions!$B$18*(Assumptions!$B$16*Assumptions!$B$17+Assumptions!$B$19*Assumptions!$B$20) -> 0 | N8: =Assumptions!$B$21+Assumptions!$B$22 -> 0 | O8: =SUM(F8,N8)+SUM(J8:M8) -> 803.6
A9: Month 6 | B9: Repositories only | C9: =Assumptions!$B$4 -> 40 | D9: =ROUND(C9/2,0) -> 20 | E9: =C9-D9 -> 20 | F9: =C9*Assumptions!$B$5 -> 800 | G9: =IF(6<Assumptions!$B$7,0,C9*Assumptions!$B$8) -> 0 | H9: =IF(G9=0,0,Assumptions!$B$10) -> 0 | I9: =MAX(G9-H9,0) -> 0 | J9: =I9*Assumptions!$B$9 -> 0 | K9: =IF(G9=0,0,Assumptions!$B$11) -> 0 | L9: =Assumptions!$B$15*Assumptions!$B$14 -> 3.6 | M9: =Assumptions!$B$18*(Assumptions!$B$16*Assumptions!$B$17+Assumptions!$B$19*Assumptions!$B$20) -> 0 | N9: =Assumptions!$B$21+Assumptions!$B$22 -> 0 | O9: =SUM(F9,N9)+SUM(J9:M9) -> 803.6
A10: Month 7 | B10: Repositories + Actions | C10: =Assumptions!$B$4 -> 40 | D10: =ROUND(C10/2,0) -> 20 | E10: =C10-D10 -> 20 | F10: =C10*Assumptions!$B$5 -> 800 | G10: =IF(7<Assumptions!$B$7,0,C10*Assumptions!$B$8) -> 20000 | H10: =IF(G10=0,0,Assumptions!$B$10) -> 0 | I10: =MAX(G10-H10,0) -> 20000 | J10: =I10*Assumptions!$B$9 -> 120 | K10: =IF(G10=0,0,Assumptions!$B$11) -> 0 | L10: =Assumptions!$B$15*Assumptions!$B$14 -> 3.6 | M10: =Assumptions!$B$18*(Assumptions!$B$16*Assumptions!$B$17+Assumptions!$B$19*Assumptions!$B$20) -> 0 | N10: =Assumptions!$B$21+Assumptions!$B$22 -> 0 | O10: =SUM(F10,N10)+SUM(J10:M10) -> 923.6
A11: Month 8 | B11: Repositories + Actions | C11: =Assumptions!$B$4 -> 40 | D11: =ROUND(C11/2,0) -> 20 | E11: =C11-D11 -> 20 | F11: =C11*Assumptions!$B$5 -> 800 | G11: =IF(8<Assumptions!$B$7,0,C11*Assumptions!$B$8) -> 20000 | H11: =IF(G11=0,0,Assumptions!$B$10) -> 0 | I11: =MAX(G11-H11,0) -> 20000 | J11: =I11*Assumptions!$B$9 -> 120 | K11: =IF(G11=0,0,Assumptions!$B$11) -> 0 | L11: =Assumptions!$B$15*Assumptions!$B$14 -> 3.6 | M11: =Assumptions!$B$18*(Assumptions!$B$16*Assumptions!$B$17+Assumptions!$B$19*Assumptions!$B$20) -> 0 | N11: =Assumptions!$B$21+Assumptions!$B$22 -> 0 | O11: =SUM(F11,N11)+SUM(J11:M11) -> 923.6
A12: Month 9 | B12: Repositories + Actions | C12: =Assumptions!$B$4 -> 40 | D12: =ROUND(C12/2,0) -> 20 | E12: =C12-D12 -> 20 | F12: =C12*Assumptions!$B$5 -> 800 | G12: =IF(9<Assumptions!$B$7,0,C12*Assumptions!$B$8) -> 20000 | H12: =IF(G12=0,0,Assumptions!$B$10) -> 0 | I12: =MAX(G12-H12,0) -> 20000 | J12: =I12*Assumptions!$B$9 -> 120 | K12: =IF(G12=0,0,Assumptions!$B$11) -> 0 | L12: =Assumptions!$B$15*Assumptions!$B$14 -> 3.6 | M12: =Assumptions!$B$18*(Assumptions!$B$16*Assumptions!$B$17+Assumptions!$B$19*Assumptions!$B$20) -> 0 | N12: =Assumptions!$B$21+Assumptions!$B$22 -> 0 | O12: =SUM(F12,N12)+SUM(J12:M12) -> 923.6
A13: Month 10 | B13: Repositories + Actions | C13: =Assumptions!$B$4 -> 40 | D13: =ROUND(C13/2,0) -> 20 | E13: =C13-D13 -> 20 | F13: =C13*Assumptions!$B$5 -> 800 | G13: =IF(10<Assumptions!$B$7,0,C13*Assumptions!$B$8) -> 20000 | H13: =IF(G13=0,0,Assumptions!$B$10) -> 0 | I13: =MAX(G13-H13,0) -> 20000 | J13: =I13*Assumptions!$B$9 -> 120 | K13: =IF(G13=0,0,Assumptions!$B$11) -> 0 | L13: =Assumptions!$B$15*Assumptions!$B$14 -> 3.6 | M13: =Assumptions!$B$18*(Assumptions!$B$16*Assumptions!$B$17+Assumptions!$B$19*Assumptions!$B$20) -> 0 | N13: =Assumptions!$B$21+Assumptions!$B$22 -> 0 | O13: =SUM(F13,N13)+SUM(J13:M13) -> 923.6
A14: Month 11 | B14: Repositories + Actions | C14: =Assumptions!$B$4 -> 40 | D14: =ROUND(C14/2,0) -> 20 | E14: =C14-D14 -> 20 | F14: =C14*Assumptions!$B$5 -> 800 | G14: =IF(11<Assumptions!$B$7,0,C14*Assumptions!$B$8) -> 20000 | H14: =IF(G14=0,0,Assumptions!$B$10) -> 0 | I14: =MAX(G14-H14,0) -> 20000 | J14: =I14*Assumptions!$B$9 -> 120 | K14: =IF(G14=0,0,Assumptions!$B$11) -> 0 | L14: =Assumptions!$B$15*Assumptions!$B$14 -> 3.6 | M14: =Assumptions!$B$18*(Assumptions!$B$16*Assumptions!$B$17+Assumptions!$B$19*Assumptions!$B$20) -> 0 | N14: =Assumptions!$B$21+Assumptions!$B$22 -> 0 | O14: =SUM(F14,N14)+SUM(J14:M14) -> 923.6
A15: Month 12 | B15: Repositories + Actions | C15: =Assumptions!$B$4 -> 40 | D15: =ROUND(C15/2,0) -> 20 | E15: =C15-D15 -> 20 | F15: =C15*Assumptions!$B$5 -> 800 | G15: =IF(12<Assumptions!$B$7,0,C15*Assumptions!$B$8) -> 20000 | H15: =IF(G15=0,0,Assumptions!$B$10) -> 0 | I15: =MAX(G15-H15,0) -> 20000 | J15: =I15*Assumptions!$B$9 -> 120 | K15: =IF(G15=0,0,Assumptions!$B$11) -> 0 | L15: =Assumptions!$B$15*Assumptions!$B$14 -> 3.6 | M15: =Assumptions!$B$18*(Assumptions!$B$16*Assumptions!$B$17+Assumptions!$B$19*Assumptions!$B$20) -> 0 | N15: =Assumptions!$B$21+Assumptions!$B$22 -> 0 | O15: =SUM(F15,N15)+SUM(J15:M15) -> 923.6
A17: 12-month total | O17: =SUM(O4:O15) -> 10363.2
A18: Base licence total | O18: =SUM(F4:F15) -> 9600
A19: Prorated Actions total (months 7-12) | O19: =SUM(J4:K15) -> 720
A20: Current monthly run rate (repos only) | O20: =O4 -> 803.6
A21: Month 7 run rate after Actions enablement | O21: =O10 -> 923.6

Sheet Scale Scenarios
A1: User Scale Scenarios and Annualised Cost
A3: Scenario | B3: Users | C3: NET users | D3: DIRECT users | E3: Base monthly | F3: Base annual | G3: Actions minutes/month | H3: Actions monthly | I3: Repos-only 6 months | J3: Actions-enabled 6 months | K3: 12-month prorated total | L3: Annual run rate after Actions
A4: 40 users | B4: 40 | C4: =ROUND(B4/2,0) -> 20 | D4: =B4-C4 -> 20 | E4: =B4*Assumptions!$B$5 -> 800 | F4: =E4*12 -> 9600 | G4: =B4*Assumptions!$B$8 -> 20000 | H4: =MAX(G4-Assumptions!$B$10,0)*Assumptions!$B$9+Assumptions!$B$11 -> 120 | I4: =E4*6 -> 4800 | J4: =(E4+H4)*6 -> 5520 | K4: =I4+J4 -> 10320 | L4: =(E4+H4)*12 -> 11040
A5: 200 users | B5: 200 | C5: =ROUND(B5/2,0) -> 100 | D5: =B5-C5 -> 100 | E5: =B5*Assumptions!$B$5 -> 4000 | F5: =E5*12 -> 48000 | G5: =B5*Assumptions!$B$8 -> 100000 | H5: =MAX(G5-Assumptions!$B$10,0)*Assumptions!$B$9+Assumptions!$B$11 -> 600 | I5: =E5*6 -> 24000 | J5: =(E5+H5)*6 -> 27600 | K5: =I5+J5 -> 51600 | L5: =(E5+H5)*12 -> 55200
A6: 400 users | B6: 400 | C6: =ROUND(B6/2,0) -> 200 | D6: =B6-C6 -> 200 | E6: =B6*Assumptions!$B$5 -> 8000 | F6: =E6*12 -> 96000 | G6: =B6*Assumptions!$B$8 -> 200000 | H6: =MAX(G6-Assumptions!$B$10,0)*Assumptions!$B$9+Assumptions!$B$11 -> 1200 | I6: =E6*6 -> 48000 | J6: =(E6+H6)*6 -> 55200 | K6: =I6+J6 -> 103200 | L6: =(E6+H6)*12 -> 110400
A7: 800 users | B7: 800 | C7: =ROUND(B7/2,0) -> 400 | D7: =B7-C7 -> 400 | E7: =B7*Assumptions!$B$5 -> 16000 | F7: =E7*12 -> 192000 | G7: =B7*Assumptions!$B$8 -> 400000 | H7: =MAX(G7-Assumptions!$B$10,0)*Assumptions!$B$9+Assumptions!$B$11 -> 2400 | I7: =E7*6 -> 96000 | J7: =(E7+H7)*6 -> 110400 | K7: =I7+J7 -> 206400 | L7: =(E7+H7)*12 -> 220800
A10: Planning note
A11: Actions estimates use 500 Linux 2-core hosted-runner minutes per user per month and $0.006/minute, with included minutes set to zero until the PO entitlement is confirmed. This deliberately avoids understating a future bill. Update the yellow/blue assumptions when pilot telemetry and contracted allowances are known.

Sheet Optional Services
A1: Optional Services: Current State and Illustrative Cost if Enabled
A3: Service | B3: Included/available in subscription | C3: Enabled now | D3: Current monthly cost | E3: Illustrative usage assumption | F3: Illustrative monthly cost | G3: Enablement horizon | H3: Primary cost driver | I3: Recommended initial budget | J3: Hard stop | K3: Notes
A4: Repositories | B4: Yes | C4: Yes | D4: =Assumptions!B4*Assumptions!B5 -> 800 | E4: 40 users; 120 repositories | F4: =D4 -> 800 | G4: Now | H4: Assigned seats | I4: $800 base licence forecast | J4: Seat approval | K4: 40 NET repos and 80 DIRECT repos; repository count itself is not used in base licence formula
A5: GitHub Actions | B5: Available | C5: No | D5: =0 -> 0 | E5: 500 Linux 2-core minutes/user/month | F5: =Assumptions!B4*Assumptions!B8*Assumptions!B9+Assumptions!B11 -> 120 | G5: Month 7 | H5: Billable runner minutes and storage | I5: =F5 -> 120 | J5: Yes during POC | K5: Reduce by included allowance once confirmed
A6: GitHub Copilot | B6: Available | C6: No | D6: =0 -> 0 | E6: 40 licensed users | F6: =Assumptions!B4*Assumptions!B14 -> 7.2 | G6: Not approved | H6: Assigned licences and AI-credit overage | I6: =0 -> 0 | J6: Yes for AI-credit overage | K6: Keep licences unassigned and overage at $0
A7: GitHub Codespaces | B7: Available | C7: No | D7: =0 -> 0 | E7: 40 users x 20 hours x 2-core plus 10 GiB storage/user | F7: =Assumptions!B4*(Assumptions!B16*Assumptions!B17+Assumptions!B19*Assumptions!B20) -> 0 | G7: Not approved | H7: Compute hours and storage | I7: =0 -> 0 | J7: Yes | K7: Disable organisation billing or restrict to named users
A8: GitHub Pages | B8: Available | C8: No | D8: =0 -> 0 | E8: No published sites | F8: =Assumptions!B21 -> 0 | G8: Not approved | H8: Validate build/bandwidth terms before use | I8: =0 -> 0 | J8: Where supported | K8: No incremental cost modelled in this plan
A9: Packages / LFS / GHAS / other | B9: Available or optional | C9: No | D9: =0 -> 0 | E9: No usage | F9: =Assumptions!B22 -> 0 | G9: Not approved | H9: Storage, transfer, active committers or SKU usage | I9: =0 -> 0 | J9: Where supported | K9: Create separate budget when scope is approved

Sheet Budgets & Alerts
A1: Final Budget and Alert Design for Two-Organisation POC
A3: Scope | B3: Product | C3: Create now | D3: Budget amount | E3: 75% response | F3: 90% response | G3: 100% response | H3: Stop usage | I3: Recipients | J3: Review | K3: Owner | L3: Rationale
A4: Enterprise | B4: Base seats | C4: Yes | D4: =Assumptions!B4*Assumptions!B5 -> 800 | E4: Check seats and pending onboarding | F4: Freeze non-critical onboarding | G4: Management approval before user 41 | H4: No | I4: Enterprise admin, billing manager, Krishna, Finance | J4: Weekly | K4: Product owner | L4: Predictable licence cost; control through seat assignment
A5: NET organisation | B5: Actions | C5: Yes | D5: $0 until month 7 | E5: Investigate any usage | F5: Disable workflows | G5: Stop usage | H5: Yes | I5: Billing manager, NET owner, platform lead | J5: Daily during tests | K5: NET owner | L5: Out of scope for first six months
A6: DIRECT organisation | B6: Actions | C6: Yes | D6: $0 until month 7 | E6: Investigate any usage | F6: Disable workflows | G6: Stop usage | H6: Yes | I6: Billing manager, DIRECT owner, platform lead | J6: Daily during tests | K6: DIRECT owner | L6: Out of scope for first six months
A7: NET organisation | B7: Codespaces | C7: Yes | D7: $0 | E7: Identify user/environment | F7: Delete stale environments | G7: Stop usage | H7: Yes | I7: Billing manager, NET owner | J7: Weekly | K7: NET owner | L7: Not enabled
A8: DIRECT organisation | B8: Codespaces | C8: Yes | D8: $0 | E8: Identify user/environment | F8: Delete stale environments | G8: Stop usage | H8: Yes | I8: Billing manager, DIRECT owner | J8: Weekly | K8: DIRECT owner | L8: Not enabled
A9: Enterprise | B9: Copilot AI credits | C9: Yes | D9: $0 | E9: Identify accidental assignment/use | F9: Revoke assignment | G9: Hard stop | H9: Yes | I9: Enterprise admin, AI owner, Finance | J9: Weekly | K9: AI owner | L9: Copilot not enabled
A10: Enterprise | B10: Other metered SKUs | C10: Yes where exposed | D10: $0 | E10: Identify SKU/owner | F10: Disable feature | G10: Stop or escalate | H10: Where supported | I10: Billing manager, platform lead | J10: Weekly | K10: Platform lead | L10: Default-deny spend
A11: NET organisation | B11: Actions after month 6 | C11: Before enablement | D11: =MAX((Assumptions!B4/2)*Assumptions!B8-Assumptions!B10/2,0)*Assumptions!B9+Assumptions!B11/2 -> 60 | E11: Investigate and reforecast | F11: Pause non-essential workflows | G11: Stop or approved exception | H11: Yes for POC | I11: Billing manager, NET owner, Finance | J11: Daily initially | K11: NET owner | L11: Half of planned Actions allowance
A12: DIRECT organisation | B12: Actions after month 6 | C12: Before enablement | D12: =MAX((Assumptions!B4/2)*Assumptions!B8-Assumptions!B10/2,0)*Assumptions!B9+Assumptions!B11/2 -> 60 | E12: Investigate and reforecast | F12: Pause non-essential workflows | G12: Stop or approved exception | H12: Yes for POC | I12: Billing manager, DIRECT owner, Finance | J12: Daily initially | K12: DIRECT owner | L12: Half of planned Actions allowance
A14: Configuration process: see the “Alert Setup Guide” worksheet for the exact GitHub navigation path, budget type, scope, threshold responses, hard-stop choice and recipients for each component.

Sheet Alert Setup Guide
A1: GitHub Enterprise POC: Budget and Alert Configuration Guide
A2: Applies to the 40-user POC, one enterprise, NET and DIRECT organisations, repositories-only for months 1-6, and planned GitHub Actions enablement from month 7.
A4: Component | B4: Current POC state | C4: Create budget when | D4: Recommended budget | E4: Budget type | F4: Budget scope | G4: GitHub admin navigation path | H4: Configuration choices | I4: 75% response | J4: 90% response | K4: 100% response | L4: Stop usage? | M4: Alert recipients | N4: Official source
A5: Enterprise base seats | B5: Enabled: 40 approved users at $20/user/month | C5: Before onboarding and whenever seat ceiling changes | D5: $800 monthly forecast; internal warning at 38 seats; management approval before user 41 | E5: Enterprise licence / seat forecast | F5: Whole enterprise | G5: Profile picture > Your enterprises > select the enterprise > Billing & Licensing > Budgets and alerts > New budget | H5: Select the enterprise licence budget if exposed. Enter seat count or amount. Enable threshold alerts. Seat assignment remains the primary control. | I5: Check joiners, leavers, duplicates and pending onboarding. | J5: Freeze non-critical onboarding and reconcile the PO forecast. | K5: Escalate any seat above 40 for management and Finance approval. | L5: No. Licence budgets normally alert rather than block. | M5: Enterprise admin, billing manager, Krishna, Finance | N5: https://docs.github.com/en/enterprise-cloud@latest/billing/concepts/budgets-and-alerts
A6: NET GitHub Actions | B6: Disabled in months 1-6; planned from month 7 | C6: Create now at $0. Replace before month 7 with approved allowance. | D6: $0 now; $60/month planning allowance from month 7 | E6: Product-level budget: GitHub Actions | F6: Organisation: NET | G6: Profile picture > Your organizations > NET > Settings > Billing & Licensing > Budgets and alerts > New budget | H6: Budget Type = Product-level; Product = Actions; Scope = NET organisation; Amount = $0 now or $60 from month 7; select Receive budget threshold alerts; select Stop usage when limit is reached during the POC. | I6: Identify workflow, runner type, repeated failures and artifact retention. | J6: Pause non-essential workflows and require owner approval. | K6: Block hosted-runner usage or approve a documented exception. | L6: Yes during POC, subject to approved critical-test exceptions. | M6: Billing manager, NET owner, platform lead, Finance | N6: https://docs.github.com/en/enterprise-cloud@latest/billing/how-tos/set-up-budgets
A7: DIRECT GitHub Actions | B7: Disabled in months 1-6; planned from month 7 | C7: Create now at $0. Replace before month 7 with approved allowance. | D7: $0 now; $60/month planning allowance from month 7 | E7: Product-level budget: GitHub Actions | F7: Organisation: DIRECT | G7: Profile picture > Your organizations > DIRECT > Settings > Billing & Licensing > Budgets and alerts > New budget | H7: Budget Type = Product-level; Product = Actions; Scope = DIRECT organisation; Amount = $0 now or $60 from month 7; select Receive budget threshold alerts; select Stop usage when limit is reached during the POC. | I7: Identify workflow, runner type, repeated failures and artifact retention. | J7: Pause non-essential workflows and require owner approval. | K7: Block hosted-runner usage or approve a documented exception. | L7: Yes during POC, subject to approved critical-test exceptions. | M7: Billing manager, DIRECT owner, platform lead, Finance | N7: https://docs.github.com/en/enterprise-cloud@latest/billing/how-tos/set-up-budgets
A8: NET Codespaces | B8: Disabled | C8: Create before POC because the service is available but out of scope. | D8: $0/month | E8: Product-level budget: Codespaces | F8: Organisation: NET | G8: Profile picture > Your organizations > NET > Settings > Billing & Licensing > Budgets and alerts > New budget | H8: Budget Type = Product-level; Product = Codespaces; Scope = NET organisation; Amount = $0; enable threshold alerts; select Stop usage when limit is reached. Also restrict or disable Codespaces technically. | I8: Identify the user, repository, machine type and environment. | J8: Stop new creation and delete stale environments or prebuilds. | K8: Block further Codespaces usage. | L8: Yes. | M8: $0 budget alerts: billing manager, NET owner, engineering owner | N8: https://docs.github.com/en/enterprise-cloud@latest/billing/how-tos/set-up-budgets
A9: DIRECT Codespaces | B9: Disabled | C9: Create before POC because the service is available but out of scope. | D9: $0/month | E9: Product-level budget: Codespaces | F9: Organisation: DIRECT | G9: Profile picture > Your organizations > DIRECT > Settings > Billing & Licensing > Budgets and alerts > New budget | H9: Budget Type = Product-level; Product = Codespaces; Scope = DIRECT organisation; Amount = $0; enable threshold alerts; select Stop usage when limit is reached. Also restrict or disable Codespaces technically. | I9: Identify the user, repository, machine type and environment. | J9: Stop new creation and delete stale environments or prebuilds. | K9: Block further Codespaces usage. | L9: Yes. | M9: $0 budget alerts: billing manager, DIRECT owner, engineering owner | N9: https://docs.github.com/en/enterprise-cloud@latest/billing/how-tos/set-up-budgets
A10: Copilot licences | B10: Disabled and unassigned | C10: Create an internal seat control now; create GitHub licence budget if exposed. | D10: $0 incremental POC assignment | E10: Enterprise licence / assignment control | F10: Whole enterprise or cost centre | G10: Profile picture > Your enterprises > select the enterprise > Billing & Licensing > Budgets and alerts > New budget | H10: Keep licences unassigned. If a licence budget is available, set the approved licence count to zero for the POC and enable alerts. | I10: Identify accidental assignment and user owner. | J10: Revoke assignment and block further assignments. | K10: Escalate any ongoing unapproved licence assignment. | L10: No. Control through licence assignment. | M10: Enterprise admin, AI owner, billing manager, Finance | N10: https://docs.github.com/en/enterprise-cloud@latest/billing/concepts/budgets-and-alerts
A11: Copilot AI credits | B11: Disabled | C11: Create now if AI-credit usage is exposed, even while Copilot licences are unassigned. | D11: $0 overage | E11: Bundled AI credits budget or Copilot AI-credit SKU budget | F11: Whole enterprise; user-level universal budget where available | G11: Profile picture > Your enterprises > select the enterprise > Billing & Licensing > Budgets and alerts > New budget | H11: Choose Bundled AI credits budget, or the specific Copilot AI-credit SKU. Set enterprise overage to $0. For user-level control, leave user blank to create a universal limit. User-level budgets always hard stop. | I11: Identify any user or feature consuming AI credits. | J11: Remove exceptions and notify the user and AI owner. | K11: Block additional AI-credit usage. | L11: Yes for metered AI-credit overage. | M11: Enterprise admin, AI owner, billing manager, Finance | N11: https://docs.github.com/en/enterprise-cloud@latest/copilot/concepts/billing/budgets-for-usage-based-billing
A12: GitHub Pages | B12: Disabled | C12: No separate budget unless a chargeable Pages-related SKU appears in Billing & Licensing. | D12: $0 planning allowance | E12: No separate budget in this model | F12: Enterprise or organisation if a future SKU is exposed | G12: Profile picture > Your enterprises > select the enterprise > Billing & Licensing > Budgets and alerts > New budget | H12: Keep Pages disabled. Review Billing & Licensing for any Pages-related metered SKU before enablement. If a chargeable SKU appears, create a product/SKU budget using the same 75/90/100 process. | I12: Confirm whether a site, build or bandwidth usage was enabled. | J12: Disable publishing and investigate ownership. | K12: Stop or escalate any chargeable use. | L12: Where supported. | M12: Billing manager, platform owner, organisation owner | N12: https://docs.github.com/en/enterprise-cloud@latest/billing/concepts/budgets-and-alerts
A13: Packages, Git LFS and other metered SKUs | B13: Disabled | C13: Create when the SKU is visible or the feature is technically available. | D13: $0 unless explicitly approved | E13: Product-level or SKU-level budget | F13: Enterprise or relevant organisation | G13: Profile picture > Your enterprises > select the enterprise > Billing & Licensing > Budgets and alerts > New budget | H13: Create only one clear budget per real exposure. Select the relevant product or SKU, set $0, enable threshold alerts and stop usage where supported. Avoid overlapping product and SKU hard-stop budgets. | I13: Identify the repository, package or transfer source. | J13: Restrict usage and remove stale content. | K13: Stop usage or escalate immediately. | L13: Yes where supported. | M13: Billing manager, platform owner, organisation owner | N13: https://docs.github.com/en/enterprise-cloud@latest/billing/how-tos/set-up-budgets
A14: Included usage alerts | B14: Enable regardless of dollar budgets | C14: Enable before the POC and keep enabled. | D14: No dollar amount; notification control | E14: Included usage alerts | F14: Enterprise account | G14: Profile picture > Your enterprises > select the enterprise > Billing & Licensing > Budgets and alerts | H14: Under Included usage alerts, select Receive alerts when included usage reaches 90% and 100%. This covers Actions minutes/storage, Packages bandwidth/storage, Git LFS bandwidth/storage, and Codespaces core hours/storage. | I14: Not applicable: included-usage alerts start at 90%. | J14: Review remaining allowance and month-end overage risk. | K14: Pause or stop the relevant service before paid overage occurs. | L14: Not a hard-stop control. | M14: Enterprise owner, organisation owners and billing managers | N14: https://docs.github.com/en/enterprise-cloud@latest/billing/concepts/budgets-and-alerts
A16: Step-by-step process in GitHub Enterprise Cloud
A17: 1 | B17: Open the correct account | E17: For enterprise controls, open the enterprise. For NET- or DIRECT-specific controls, open that organisation.
A18: 2 | B18: Navigate to billing | E18: Enterprise: Billing & Licensing tab. Organisation: Settings > Billing & Licensing.
A19: 3 | B19: Open Budgets and alerts | E19: Review existing budgets first. Do not create an overlapping hard-stop budget for the same product and usage scope.
A20: 4 | B20: Select New budget | E20: Choose Product-level budget, SKU-level budget, or Bundled AI credits budget.
A21: 5 | B21: Set scope | E21: Choose Enterprise, NET organisation, DIRECT organisation, repository, cost centre, or users, as appropriate.
A22: 6 | B22: Set amount | E22: Use $0 for disabled/out-of-scope metered products. Before Actions month 7, replace $0 with the approved NET and DIRECT allowances.
A23: 7 | B23: Choose enforcement | E23: For POC metered services, select Stop usage when budget limit is reached where available and operationally acceptable.
A24: 8 | B24: Enable alerts | E24: Select Receive budget threshold alerts. GitHub sends alerts at 75%, 90% and 100% by email and displays a banner in GitHub.
A25: 9 | B25: Set recipients | E25: Add the billing manager, enterprise/organisation owner, Krishna, platform owner and Finance. Do not rely on one administrator.
A26: 10 | B26: Enable included usage alerts | E26: On the same page, enable alerts at 90% and 100% of included usage for Actions, Packages, Git LFS and Codespaces.
A27: 11 | B27: Record evidence | E27: Capture a screenshot or export showing product, scope, amount, hard-stop setting and recipients. Link it to the POC Jira/decision record.
A28: 12 | B28: Operate the control | E28: Review billing daily during active tests, weekly otherwise, and complete a Finance pre-close before invoice issue.
A30: Important POC notes
A31: • Budgets apply only to metered usage from the date they are created. Create the $0 controls before the POC starts because earlier usage is not covered retroactively.
A32: • If Stop usage when budget limit is reached is not selected, GitHub sends alerts but does not stop consumption.
A33: • Budget threshold alerts and included-usage alerts are different. Enable both.
A34: • For the base 40 enterprise seats, the strongest control is approved seat assignment through Okta/Azure AD plus weekly reconciliation, not a repository quota.
A35: • Teams should be used for access mapping. For this POC, budgets should stay at enterprise or organisation level unless one repository has a separately approved cost owner.

Sheet POC Checklist
A1: Implementation and Month-End Assurance Checklist
A3: ID | B3: When | C3: Check | D3: Expected evidence | E3: Owner | F3: Status | G3: Escalation trigger | H3: Jira / decision | I3: Notes
A4: 01 | B4: Before onboarding | C4: Confirm 40-seat PO baseline | D4: PO rate $20/user/month and billing cycle recorded | E4: Finance + Product owner | F4: Open | G4: Price or entitlement unclear
A5: 02 | B5: Before onboarding | C5: Confirm NET and DIRECT allocation | D5: 40 and 80 repositories; user/team mapping documented | E5: Enterprise admin | F5: Open | G5: Unowned repository/team
A6: 03 | B6: Before onboarding | C6: Validate Okta/Azure AD SSO and provisioning | D6: Group-to-organisation/team mapping; deprovision test | E6: IAM owner | F6: Open | G6: User can access after deprovision
A7: 04 | B7: Before POC | C7: Disable non-repository products | D7: Actions, Codespaces, Copilot, Pages and other metered features verified off | E7: Enterprise admin | F7: Open | G7: Any out-of-scope feature usable
A8: 05 | B8: Before POC | C8: Create $0 budgets | D8: Organisation Actions/Codespaces and enterprise AI/other budgets captured | E8: Billing manager | F8: Open | G8: Metered exposure without budget
A9: 06 | B9: Daily during active POC | C9: Review billing dashboard | D9: Spend by enterprise, organisation, product and SKU | E9: Krishna | F9: Open | G9: Unknown SKU or >20% daily jump
A10: 07 | B10: Weekly | C10: Reconcile seats with Okta/Azure AD | D10: Assigned vs approved users; leavers removed | E10: Product owner | F10: Open | G10: More than 40 assigned seats
A11: 08 | B11: Month 5 | C11: Prepare Actions budget | D11: Pilot workload, included minutes and runner strategy confirmed | E11: Platform lead | F11: Open | G11: Actions enablement without agreed budget
A12: 09 | B12: Month 6 | C12: Approve Actions rollout | D12: NET and DIRECT budgets, owners and stop-usage controls live | E12: Management + Finance | F12: Open | G12: No signed cost envelope
A13: 10 | B13: Before month end | C13: Invoice pre-close | D13: Forecast reconciled to billing export | E13: Finance + Krishna | F13: Open | G13: >10% unexplained variance
